uncurl/__init__.py
uncurl/api.py
uncurl/bin.py
puncurl-0.0.13.dist-info/LICENSE
puncurl-0.0.13.dist-info/METADATA
puncurl-0.0.13.dist-info/WHEEL
puncurl-0.0.13.dist-info/entry_points.txt
puncurl-0.0.13.dist-info/top_level.txt
puncurl-0.0.13.dist-info/RECORD
