Metadata-Version: 2.1
Name: puncurl
Version: 0.0.13
Summary: A library to convert curl requests to python-requests.
Home-page: https://github.com/pancaprima/uncurl
Author: Fernanda Panca Prima
Author-email: pancaprima8@gmail.com
License: UNKNOWN
Platform: UNKNOWN
Requires-Dist: xerox
Requires-Dist: six
